mlwizard/__init__.py
mlwizard/automate.py
mlwizard/build_model.py
mlwizard/date.py
mlwizard/eda.py
mlwizard/output_dataset.py
mlwizard/preprocessing.py
mlwizard-1.0.1.dist-info/LICENSE
mlwizard-1.0.1.dist-info/METADATA
mlwizard-1.0.1.dist-info/WHEEL
mlwizard-1.0.1.dist-info/top_level.txt
mlwizard-1.0.1.dist-info/RECORD
