Metadata-Version: 2.1
Name: mlwizard
Version: 1.0.1
Summary: Let's make building machine learning models the complex way, easy.
Author: TechLeo (Onyiriuba Leonard Chukwubuikem)
Author-email: <techleo.ng@outlook.com>
License: MIT
Keywords: machine learning,data science,data preprocessing,supervised learning,data exploration,ML framework,data cleaning,regression,classification,machine learning toolkit
Classifier: Development Status :: 4 - Beta
Classifier: Intended Audience :: End Users/Desktop
Classifier: Intended Audience :: Developers
Classifier: Intended Audience :: Science/Research
Classifier: License :: OSI Approved :: MIT License
Classifier: Programming Language :: Python :: 3
Classifier: Programming Language :: Python :: 3.6
Classifier: Programming Language :: Python :: 3.7
Classifier: Programming Language :: Python :: 3.8
Classifier: Programming Language :: Python :: 3.9
Classifier: Operating System :: Unix
Classifier: Operating System :: MacOS :: MacOS X
Classifier: Operating System :: Microsoft :: Windows
Requires-Python: >=3.0
License-File: LICENSE
Requires-Dist: datatable ==1.1.0
Requires-Dist: imbalanced-learn ==0.10.1
Requires-Dist: imblearn ==0.0
Requires-Dist: matplotlib >=3.4.3
Requires-Dist: numpy >=1.22
Requires-Dist: pandas >=1.2.4
Requires-Dist: scikit-learn >=0.24.2
Requires-Dist: seaborn ==0.11.2
Requires-Dist: setuptools >=65.5.1
Requires-Dist: sweetviz ==2.1.4
Requires-Dist: ydata-profiling ==4.1.2
